ITMO_FS/__init__.py
ITMO_FS/_version.py
ITMO_FS/embedded/MOS.py
ITMO_FS/embedded/__init__.py
ITMO_FS/ensembles/__init__.py
ITMO_FS/ensembles/measure_based/WeightBased.py
ITMO_FS/ensembles/measure_based/__init__.py
ITMO_FS/ensembles/measure_based/fusion_functions.py
ITMO_FS/ensembles/model_based/__init__.py
ITMO_FS/ensembles/model_based/best_sum.py
ITMO_FS/ensembles/ranking_based/Mixed.py
ITMO_FS/ensembles/ranking_based/__init__.py
ITMO_FS/ensembles/ranking_based/fusion_functions.py
ITMO_FS/filters/__init__.py
ITMO_FS/filters/multivariate/DISRwithMassive.py
ITMO_FS/filters/multivariate/FCBF.py
ITMO_FS/filters/multivariate/MultivariateFilter.py
ITMO_FS/filters/multivariate/STIR.py
ITMO_FS/filters/multivariate/TraceRatioFisher.py
ITMO_FS/filters/multivariate/__init__.py
ITMO_FS/filters/multivariate/measures.py
ITMO_FS/filters/multivariate/mimaga.py
ITMO_FS/filters/sparse/MCFS.py
ITMO_FS/filters/sparse/NDFS.py
ITMO_FS/filters/sparse/RFS.py
ITMO_FS/filters/sparse/SPEC.py
ITMO_FS/filters/sparse/UDFS.py
ITMO_FS/filters/sparse/__init__.py
ITMO_FS/filters/univariate/UnivariateFilter.py
ITMO_FS/filters/univariate/VDM.py
ITMO_FS/filters/univariate/__init__.py
ITMO_FS/filters/univariate/measures.py
ITMO_FS/filters/unsupervised/__init__.py
ITMO_FS/filters/unsupervised/trace_ratio_laplacian.py
ITMO_FS/hybrid/Melif.py
ITMO_FS/hybrid/__init__.py
ITMO_FS/hybrid/filter_wrapper_hybrid.py
ITMO_FS/utils/DataChecker.py
ITMO_FS/utils/__init__.py
ITMO_FS/utils/data_check.py
ITMO_FS/utils/functions.py
ITMO_FS/utils/information_theory.py
ITMO_FS/utils/qpfs_body.py
ITMO_FS/wrappers/__init__.py
ITMO_FS/wrappers/wrapper_utils.py
ITMO_FS/wrappers/deterministic/AddDelWrapper.py
ITMO_FS/wrappers/deterministic/BackwardSelection.py
ITMO_FS/wrappers/deterministic/RecursiveElimination.py
ITMO_FS/wrappers/deterministic/SequentialForwardSelection.py
ITMO_FS/wrappers/deterministic/__init__.py
ITMO_FS/wrappers/deterministic/qpfs_wrapper.py
ITMO_FS/wrappers/randomized/HillClimbing.py
ITMO_FS-0.3.3.dist-info/LICENSE
ITMO_FS-0.3.3.dist-info/METADATA
ITMO_FS-0.3.3.dist-info/WHEEL
ITMO_FS-0.3.3.dist-info/top_level.txt
ITMO_FS-0.3.3.dist-info/RECORD
